[
  {
    "caller": "POST /auth/",
    "callee": "SELECT admins.`idAdmin` AS `admins_idAdmin`, admins.email AS admins_email, admins.password AS admins_password, admins.`lastName` AS `admins_lastName`, admins.`firstName` AS `admins_firstName`, admins.`phoneNumber` AS `admins_phoneNumber`, admins.photo AS admins_photo \nFROM admins \nWHERE admins.email = %(email_1)s \n LIMIT %(param_1)s"
  },
  {
    "caller": "POST /auth/",
    "callee": "SELECT client.`idClient` AS `client_idClient`, client.`lastName` AS `client_lastName`, client.`firstName` AS `client_firstName`, client.email AS client_email, client.password AS client_password, client.phone AS client_phone, client.user_img AS client_user_img, client.`creationDate` AS `client_creationDate`, client.is_admin AS client_is_admin \nFROM client \nWHERE client.email = %(email_1)s \n LIMIT %(param_1)s"
  },
  {
    "caller": "POST /auth/",
    "callee": "app/controllers"
  }
]